LICENSE
README.md
wagtailagenda/__init__.py
wagtailagenda/admin.py
wagtailagenda/apps.py
wagtailagenda/migrations/0001_initial.py
wagtailagenda/migrations/0002_auto_20211020_0049.py
wagtailagenda/migrations/__init__.py
wagtailagenda/models.py
wagtailagenda/templates/wagtailagenda/activity.html
wagtailagenda/templates/wagtailagenda/agenda.html
wagtailagenda/tests.py
wagtailagenda/views.py
wagtailagenda-0.1.1.dist-info/LICENSE
wagtailagenda-0.1.1.dist-info/WHEEL
wagtailagenda-0.1.1.dist-info/METADATA
wagtailagenda-0.1.1.dist-info/RECORD
