Metadata-Version: 2.1
Name: wagtailagenda
Version: 0.1.1
Summary: An aganda app for Wagtail
Home-page: https://framagit.org/SebGen/wagtail-agenda
License: LGPL-3.0-only
Author: Sébastien Gendre
Author-email: seb@k-7.ch
Requires-Python: >=3.9,<4.0
Classifier: License :: OSI Approved :: GNU Lesser General Public License v3 (LGPLv3)
Classifier: Programming Language :: Python :: 3
Classifier: Programming Language :: Python :: 3.9
Requires-Dist: ics (>=0.7,<0.8)
Requires-Dist: wagtail (>=2.14.1,<3.0.0)
Requires-Dist: wagtailperson (>=0.13.2,<0.14.0)
Project-URL: Repository, https://framagit.org/SebGen/wagtail-agenda
